lcsb_pbin/__init__.py
lcsb_pbin-0.0.4.dist-info/LICENSE
lcsb_pbin-0.0.4.dist-info/METADATA
lcsb_pbin-0.0.4.dist-info/WHEEL
lcsb_pbin-0.0.4.dist-info/top_level.txt
lcsb_pbin-0.0.4.dist-info/RECORD
