Metadata-Version: 2.1
Name: lcsb-pbin
Version: 0.0.4
Summary: Small lib to interact with LCSB privatebin
Home-page: https://git-r3lab.uni.lu/core-services/lcsb-private-bin
Author: LCSB sysadmin
Author-email: lcsb-sysadmins@uni.lu
License: UNKNOWN
Platform: UNKNOWN
Classifier: Programming Language :: Python :: 3
Classifier: License :: OSI Approved :: MIT License
Classifier: Operating System :: OS Independent
Requires-Python: >=3.6
License-File: LICENSE
Requires-Dist: PBinCLI (==0.3.1)
